my_package/__init__.py
my_package/core.py
my_unique_package_name_change_this-0.0.1.dist-info/METADATA
my_unique_package_name_change_this-0.0.1.dist-info/WHEEL
my_unique_package_name_change_this-0.0.1.dist-info/top_level.txt
my_unique_package_name_change_this-0.0.1.dist-info/RECORD
