Metadata-Version: 2.4
Name: my-unique-package-name-change-this
Version: 0.0.1
Summary: Short description of my package
Author-email: Your Name <you@example.com>
Requires-Python: >=3.9
